{
	"name": "3DShape9",
	"plugin-id": "Shape3D",
	"sid": 841996535705547,
	"isGlobal": false,
	"instanceVariables": [],
	"behaviorTypes": [],
	"effectTypes": [],
	"animations": {
		"items": [
			{
				"frames": [
					{
						"width": 120,
						"height": 120,
						"originX": 0.5,
						"originY": 0.5,
						"originalSource": "",
						"exportFormat": "png",
						"exportQuality": 0.8,
						"imageSpriteId": 1186624,
						"useCollisionPoly": true,
						"duration": 1
					},
					{
						"width": 120,
						"height": 120,
						"originX": 0.5,
						"originY": 0.5,
						"originalSource": "",
						"exportFormat": "png",
						"exportQuality": 0.8,
						"imageSpriteId": 9057965,
						"useCollisionPoly": true,
						"duration": 1
					},
					{
						"width": 197,
						"height": 610,
						"originX": 0.5279187817258884,
						"originY": 0.4934426229508197,
						"originalSource": "",
						"exportFormat": "png",
						"exportQuality": 0.8,
						"imageSpriteId": 8612938,
						"collisionPoly": {
							"points": [
								0,
								0,
								0.5279187817258884,
								0,
								1,
								0,
								1,
								0.4934426229508197,
								1,
								1,
								0.5279187817258884,
								1,
								0,
								1,
								0,
								0.4934426229508197
							]
						},
						"useCollisionPoly": true,
						"duration": 1
					},
					{
						"width": 120,
						"height": 120,
						"originX": 0.5,
						"originY": 0.5,
						"originalSource": "",
						"exportFormat": "png",
						"exportQuality": 0.8,
						"imageSpriteId": 89564,
						"useCollisionPoly": true,
						"duration": 1
					},
					{
						"width": 120,
						"height": 120,
						"originX": 0.5,
						"originY": 0.5,
						"originalSource": "",
						"exportFormat": "png",
						"exportQuality": 0.8,
						"imageSpriteId": 348739,
						"useCollisionPoly": true,
						"duration": 1
					},
					{
						"width": 120,
						"height": 120,
						"originX": 0.5,
						"originY": 0.5,
						"originalSource": "",
						"exportFormat": "png",
						"exportQuality": 0.8,
						"imageSpriteId": 958802,
						"useCollisionPoly": true,
						"duration": 1
					}
				],
				"sid": 950138083438261,
				"name": "Animation 1",
				"isLooping": false,
				"isPingPong": false,
				"repeatCount": 1,
				"repeatTo": 0,
				"speed": 5
			}
		],
		"subfolders": []
	}
}