{
	"name": "Spikes",
	"plugin-id": "Sprite",
	"sid": 772228511602804,
	"isGlobal": false,
	"instanceVariables": [],
	"behaviorTypes": [],
	"effectTypes": [],
	"animations": {
		"items": [
			{
				"frames": [
					{
						"width": 72,
						"height": 37,
						"originX": 0.5,
						"originY": 0.02702702702702703,
						"originalSource": "",
						"exportFormat": "png",
						"exportQuality": 0.8,
						"imageSpriteId": 3024862,
						"collisionPoly": {
							"points": [
								0.7361111111111112,
								0.4864864864864865,
								0.5,
								0.05405405405405406,
								0.25,
								0.4864864864864865,
								0.9722222222222222,
								0.9459459459459459,
								0.5,
								0.9459459459459459,
								0.013888888888888888,
								0.9459459459459459
							]
						},
						"useCollisionPoly": true,
						"duration": 1
					}
				],
				"sid": 860999240833284,
				"name": "Animation 1",
				"isLooping": false,
				"isPingPong": false,
				"repeatCount": 1,
				"repeatTo": 0,
				"speed": 5
			}
		],
		"subfolders": []
	}
}